<?xml version="1.0" encoding="UTF-8" standalone="no"?><EMPLEADOS>
    <EMPLEADO>
        <NOMBRE>LUIS MIGUEL</NOMBRE>
        <APELLIDOS>GALLARDO LEON</APELLIDOS>
        <NIF>5674179P</NIF>
        <EMPRESA>DATATONIC, S.A.</EMPRESA>
        <DIRECCION>HERMANOS ARAGON , CALLE</DIRECCION>
        <CP>11690</CP>
        <LOCALIDAD>OLVERA</LOCALIDAD>
        <TLF_FIJO>95630316</TLF_FIJO>
        <TLF_MOVIL>69619915</TLF_MOVIL>
        <SALARIO>7000</SALARIO>
    </EMPLEADO>
    <EMPLEADO>
        <NOMBRE>MIGUEL</NOMBRE>
        <APELLIDOS>BERENGUEL MARQUINA</APELLIDOS>
        <NIF>6182669F</NIF>
        <EMPRESA>MAGARIIT SERVICES, S.A.</EMPRESA>
        <DIRECCION>ALCALA LA REAL , CALLE</DIRECCION>
        <CP>11640</CP>
        <LOCALIDAD>BORNOS</LOCALIDAD>
        <TLF_FIJO>96304400</TLF_FIJO>
        <TLF_MOVIL>62676864</TLF_MOVIL>
    </EMPLEADO>
</EMPLEADOS>